[{"type":"free","url":"https://3dsky.org/3dmodels/category/clock?style=all&order=free&page=1"},{"type":"free","url":"https://3dsky.org/3dmodels/category/clock?style=all&order=free&page=2"},{"type":"free","url":"https://3dsky.org/3dmodels/category/clock?style=all&order=free&page=3"},{"type":"free","url":"https://3dsky.org/3dmodels/category/clock?style=all&order=free&page=4"},{"type":"free","url":"https://3dsky.org/3dmodels/category/clock?style=all&order=free&page=5"},{"type":"free","url":"https://3dsky.org/3dmodels/category/clock?style=all&order=free&page=6"},{"type":"free","url":"https://3dsky.org/3dmodels/category/clock?style=all&order=free&page=7"},{"type":"free","url":"https://3dsky.org/3dmodels/category/clock?style=all&order=free&page=8"},{"type":"free","url":"https://3dsky.org/3dmodels/category/clock?style=all&order=free&page=9"},{"type":"free","url":"https://3dsky.org/3dmodels/category/clock?style=all&order=free&page=10"},{"type":"free","url":"https://3dsky.org/3dmodels/category/clock?style=all&order=free&page=11"},{"type":"free","url":"https://3dsky.org/3dmodels/category/clock?style=all&order=free&page=12"},{"type":"free","url":"https://3dsky.org/3dmodels/category/clock?style=all&order=free&page=13"},{"type":"free","url":"https://3dsky.org/3dmodels/category/clock?style=all&order=free&page=14"},{"type":"free","url":"https://3dsky.org/3dmodels/category/clock?style=all&order=free&page=15"},{"type":"free","url":"https://3dsky.org/3dmodels/category/clock?style=all&order=free&page=16"},{"type":"free","url":"https://3dsky.org/3dmodels/category/clock?style=all&order=free&page=17"},{"type":"free","url":"https://3dsky.org/3dmodels/category/clock?style=all&order=free&page=18"},{"type":"profi","url":"https://3dsky.org/3dmodels/category/clock?style=all&order=profi&page=1"},{"type":"profi","url":"https://3dsky.org/3dmodels/category/clock?style=all&order=profi&page=2"},{"type":"profi","url":"https://3dsky.org/3dmodels/category/clock?style=all&order=profi&page=3"},{"type":"profi","url":"https://3dsky.org/3dmodels/category/clock?style=all&order=profi&page=4"},{"type":"profi","url":"https://3dsky.org/3dmodels/category/clock?style=all&order=profi&page=5"},{"type":"profi","url":"https://3dsky.org/3dmodels/category/clock?style=all&order=profi&page=6"},{"type":"profi","url":"https://3dsky.org/3dmodels/category/clock?style=all&order=profi&page=7"},{"type":"profi","url":"https://3dsky.org/3dmodels/category/clock?style=all&order=profi&page=8"},{"type":"profi","url":"https://3dsky.org/3dmodels/category/clock?style=all&order=profi&page=9"},{"type":"profi","url":"https://3dsky.org/3dmodels/category/clock?style=all&order=profi&page=10"},{"type":"profi","url":"https://3dsky.org/3dmodels/category/clock?style=all&order=profi&page=11"},{"type":"profi","url":"https://3dsky.org/3dmodels/category/clock?style=all&order=profi&page=12"},{"type":"profi","url":"https://3dsky.org/3dmodels/category/clock?style=all&order=profi&page=13"},{"type":"profi","url":"https://3dsky.org/3dmodels/category/clock?style=all&order=profi&page=14"},{"type":"profi","url":"https://3dsky.org/3dmodels/category/clock?style=all&order=profi&page=15"},{"type":"profi","url":"https://3dsky.org/3dmodels/category/clock?style=all&order=profi&page=16"},{"type":"profi","url":"https://3dsky.org/3dmodels/category/clock?style=all&order=profi&page=17"},{"type":"profi","url":"https://3dsky.org/3dmodels/category/clock?style=all&order=profi&page=18"}]